data_mig/__init__.py
data_mig/csvtools/__init__.py
data_mig/csvtools/loader.py
data_mig/jobs/__init__.py
data_mig/jobs/runner.py
data_mig/salesforce/__init__.py
data_mig/salesforce/bulk.py
data_mig/salesforce/bulkv2.py
data_mig/salesforce/fileloader.py
data_mig/salesforce/loader.py
data_mig/salesforce/metadata.py
data_mig/salesforce/oauth.py
data_mig/salesforce/tools.py
data_mig/salesforce/wsdl/__init__.py
data_mig/salesforce/wsdl/metadata.xml
data_mig/salesforce/wsdl/tooling.xml
data_mig/sql/__init__.py
data_mig/sql/loader.py
data_mig/sql/tools.py
data_mig/tests/__init__.py
data_mig/tests/faker.py
data_mig/tests/jobs/__init__.py
data_mig/tests/jobs/runner.py
data_mig/tests/notifications.py
data_mig/tests/salesforce/__init__.py
data_mig/tests/salesforce/bulk.py
data_mig/tests/salesforce/metadata.py
data_mig/tests/salesforce/salesforce.py
data_mig/tests/sql/__init__.py
data_mig/tests/sql/sql.py
data_mig/utils/__init__.py
data_mig/utils/caseinsensitivelist.py
data_mig/utils/config.py
data_mig/utils/exceptions.py
data_mig/utils/job.py
data_mig/utils/logging.py
data_mig/utils/sql.py
data_mig-0.1.8.dist-info/WHEEL
data_mig-0.1.8.dist-info/METADATA
data_mig-0.1.8.dist-info/RECORD
