Metadata-Version: 2.1
Name: data-mig
Version: 0.1.8
Summary: Arroyo: The Fíonta Data Migration Toolkit
Author: David Manuel
Author-email: dmanuel@fionta.com
Requires-Python: >=3.10,<4.0
Classifier: Programming Language :: Python :: 3
Classifier: Programming Language :: Python :: 3.10
Requires-Dist: PyYAML (>=6.0,<7.0)
Requires-Dist: SQLAlchemy (>=1.4.39,<2.0.0)
Requires-Dist: pandas (>=1.4.3,<2.0.0)
Requires-Dist: progressbar2 (>=4.0.0,<5.0.0)
Requires-Dist: pyodbc (>=4.0.34,<5.0.0)
Requires-Dist: pyotp (>=2.6.0,<3.0.0)
Requires-Dist: pytest (>=7.1.2,<8.0.0)
Requires-Dist: pytest-mock (>=3.8.2,<4.0.0)
Requires-Dist: requests (>=2.28.1,<3.0.0)
Requires-Dist: simple-salesforce (>=1.12.1,<2.0.0)
Requires-Dist: simplejson (>=3.17.6,<4.0.0)
Requires-Dist: sqlparse (>=0.4.2,<0.5.0)
Requires-Dist: validate_email (>=1.3,<2.0)
Requires-Dist: xlrd (>=2.0.1,<3.0.0)
Requires-Dist: zeep (>=4.1.0,<5.0.0)
